leaguepedia_parser/__init__.py
leaguepedia_parser/logger.py
leaguepedia_parser/parsers/game_parser.py
leaguepedia_parser/parsers/team_parser.py
leaguepedia_parser/site/leaguepedia.py
leaguepedia_parser/transmuters/field_names.py
leaguepedia_parser/transmuters/game.py
leaguepedia_parser/transmuters/game_players.py
leaguepedia_parser/transmuters/picks_bans.py
leaguepedia_parser/transmuters/tournament.py
leaguepedia_parser-2.0.1.dist-info/LICENSE
leaguepedia_parser-2.0.1.dist-info/WHEEL
leaguepedia_parser-2.0.1.dist-info/METADATA
leaguepedia_parser-2.0.1.dist-info/RECORD
